{
   "CodeGenerationMode": 2,
   "ContextClassName": "OSSContext",
   "ContextNamespace": null,
   "DefaultDacpacSchema": null,
   "FilterSchemas": false,
   "IncludeConnectionString": true,
   "ModelNamespace": null,
   "OutputContextPath": null,
   "OutputPath": ".\/Entity",
   "PreserveCasingWithRegex": true,
   "ProjectRootNamespace": "OSS.Data",
   "Schemas": null,
   "SelectedHandlebarsLanguage": 0,
   "SelectedToBeGenerated": 0,
   "Tables": [
      {
         "Name": "[dbo].[Categories]",
         "ObjectType": 0
      },
      {
         "Name": "[dbo].[FootwaerDetails]",
         "ObjectType": 0
      },
      {
         "Name": "[dbo].[Manufacturers]",
         "ObjectType": 0
      }
   ],
   "UiHint": "IN-LT-17262\\SQL2019.OSS",
   "UseBoolPropertiesWithoutDefaultSql": false,
   "UseDatabaseNames": false,
   "UseDbContextSplitting": false,
   "UseFluentApiOnly": true,
   "UseHandleBars": false,
   "UseHierarchyId": false,
   "UseInflector": false,
   "UseLegacyPluralizer": false,
   "UseManyToManyEntity": false,
   "UseNoConstructor": false,
   "UseNoDefaultConstructor": false,
   "UseNoNavigations": false,
   "UseNoObjectFilter": false,
   "UseNodaTime": false,
   "UseNullableReferences": false,
   "UseSchemaFolders": false,
   "UseSpatial": false,
   "UseT4": false
}